dataglove/DataGloveWindows.dll
dataglove/__init__.py
dataglove/dataglove.py
dataglove-0.3.0.dist-info/LICENSE
dataglove-0.3.0.dist-info/METADATA
dataglove-0.3.0.dist-info/WHEEL
dataglove-0.3.0.dist-info/top_level.txt
dataglove-0.3.0.dist-info/RECORD
