Metadata-Version: 2.1
Name: dataglove
Version: 0.3.0
Summary: 64-bit Python Module of the DataGlove API.
Home-page: UNKNOWN
Author: BeBop Sensors
Author-email: code@bebopsensors.com
License: UNKNOWN
Platform: UNKNOWN
Classifier: Programming Language :: Python :: 3
Classifier: License :: OSI Approved :: MIT License
Classifier: Operating System :: Microsoft :: Windows
Requires-Python: >=3
License-File: LICENSE
